gaia/__init__.py
gaia/server.py
gaia.py-0.1.0.dist-info/LICENSE
gaia.py-0.1.0.dist-info/LICENSE.bak
gaia.py-0.1.0.dist-info/METADATA
gaia.py-0.1.0.dist-info/WHEEL
gaia.py-0.1.0.dist-info/top_level.txt
gaia.py-0.1.0.dist-info/RECORD
