Metadata-Version: 2.1
Name: gaia.py
Version: 0.1.0
Summary: Gaia, the very framework to make gRPC services
Home-page: https://github.com/kaelzhang/gaia
Author: kaelzhang
Author-email: 
License: MIT
Keywords: gaia grpc framework server client
Platform: UNKNOWN
Classifier: Topic :: Software Development :: Libraries :: Python Modules
Classifier: Programming Language :: Python :: 3.7
Classifier: Programming Language :: Python :: 3.8
Classifier: Programming Language :: Python :: Implementation :: PyPy
Classifier: Topic :: Software Development :: Libraries :: Python Modules
Classifier: License :: OSI Approved :: MIT License
Requires-Python: >=3.7
